[
    {
        "_id": "66e87dce067b01942ecb4a55",
        "id": "889eccc7-10d2-4e8d-bdd3-efd883993a1f",
        "images": [
            "https://i.imgur.com/UsSFbtZ.png"
        ],
        "text": [
            "Habilidad"
        ]
    },
    {
        "_id": "66e87dcf067b01942ecb4a56",
        "id": "0c06b8c6-47a9-47e0-ba63-14aa44e8edd0",
        "images": [
            "https://i.imgur.com/jZ0LpkO.png"
        ],
        "text": [
            "Habitación"
        ]
    },
    {
        "_id": "66e87dd1067b01942ecb4a57",
        "id": "40a629a0-0e29-40e9-9dad-a8e8652d24f0",
        "images": [
            "https://i.imgur.com/7GwzYdG.png"
        ],
        "text": [
            "Hábito",
            "habito",
            "habitas",
            "habita",
            "habitamos",
            "habitáis",
            "habitan",
            "habitás",
            "habitaba",
            "habitabas",
            "habitábamos",
            "habitabais",
            "habitaban",
            "habité",
            "habitaste",
            "habitó",
            "habitasteis",
            "habitaron",
            "habitaré",
            "habitarás",
            "habitará",
            "habitaremos",
            "habitaréis",
            "habitarán",
            "habitaría",
            "habitarías",
            "habitaríamos",
            "habitaríais",
            "habitarían",
            "habitar",
            "habitando",
            "habitado",
            "–"
        ]
    },
    {
        "_id": "66e87dd4067b01942ecb4a58",
        "id": "92901646-924d-4036-b8ce-a496896d2323",
        "images": [
            "https://i.imgur.com/kYfNQhm.png"
        ],
        "text": [
            "Hablar",
            "hablo",
            "hablas",
            "habla",
            "hablamos",
            "habláis",
            "hablan",
            "hablás",
            "hablaba",
            "hablabas",
            "hablábamos",
            "hablabais",
            "hablaban",
            "hablé",
            "hablaste",
            "habló",
            "hablasteis",
            "hablaron",
            "hablaré",
            "hablarás",
            "hablará",
            "hablaremos",
            "hablaréis",
            "hablarán",
            "hablaría",
            "hablarías",
            "hablaríamos",
            "hablaríais",
            "hablarían",
            "hablar",
            "hablando",
            "hablado",
            "hablarse",
            "Parlotear",
            "parloteo",
            "parloteas",
            "parlotea",
            "parloteamos",
            "parloteáis",
            "parlotean",
            "parloteás",
            "parloteaba",
            "parloteabas",
            "parloteábamos",
            "parloteabais",
            "parloteaban",
            "parloteé",
            "parloteaste",
            "parloteó",
            "parloteasteis",
            "parlotearon",
            "parlotearé",
            "parlotearás",
            "parloteará",
            "parlotearemos",
            "parlotearéis",
            "parlotearán",
            "parlotearía",
            "parlotearías",
            "parlotearíamos",
            "parlotearíais",
            "parlotearían",
            "parlotear",
            "parloteando",
            "parloteado",
            "–",
            "Conversar",
            "converso",
            "conversas",
            "conversa",
            "conversamos",
            "conversáis",
            "conversan",
            "conversás",
            "conversaba",
            "conversabas",
            "conversábamos",
            "conversabais",
            "conversaban",
            "conversé",
            "conversaste",
            "conversó",
            "conversasteis",
            "conversaron",
            "conversaré",
            "conversarás",
            "conversará",
            "conversaremos",
            "conversaréis",
            "conversarán",
            "conversaría",
            "conversarías",
            "conversaríamos",
            "conversaríais",
            "conversarían",
            "conversar",
            "conversando",
            "conversado",
            "–"
        ]
    },
    {
        "_id": "66e87dd6067b01942ecb4a59",
        "id": "3be3a633-050f-420b-8355-c4555951dfee",
        "images": [
            "https://i.imgur.com/K2gZ79J.png"
        ],
        "text": [
            "Hace Mucho Tiempo"
        ]
    },
    {
        "_id": "66e87dd7067b01942ecb4a5a",
        "id": "0e2aee9d-7f02-4242-8daf-f204da37b8fb",
        "images": [
            "https://i.imgur.com/YKn1jUl.png"
        ],
        "text": [
            "Hacer",
            "hago",
            "haces",
            "hace",
            "hacemos",
            "hacéis",
            "hacen",
            "hacés",
            "hacía",
            "hacías",
            "hacíamos",
            "hacíais",
            "hacían",
            "hice",
            "hiciste",
            "hizo",
            "hicimos",
            "hicisteis",
            "hicieron",
            "haré",
            "harás",
            "hará",
            "haremos",
            "haréis",
            "harán",
            "haría",
            "harías",
            "haríamos",
            "haríais",
            "harían",
            "hacer",
            "haciendo",
            "hecho",
            "hacerse"
        ]
    },
    {
        "_id": "66e87dd9067b01942ecb4a5b",
        "id": "4c437471-8f7b-431e-a292-815cc29633de",
        "images": [
            "https://i.imgur.com/H3tGZyq.png"
        ],
        "text": [
            "Hacha",
            "Azuela"
        ]
    },
    {
        "_id": "66e87ddb067b01942ecb4a5c",
        "id": "04733c74-5cfd-4632-a592-849b1b2af957",
        "images": [
            "https://i.imgur.com/JZsbXoP.png"
        ],
        "text": [
            "Halcón"
        ]
    },
    {
        "_id": "66e87ddc067b01942ecb4a5d",
        "id": "4de7422d-b13a-47ba-ad4f-e1e606ad6a90",
        "images": [
            "https://i.imgur.com/7Q9JSnA.png",
            "https://i.imgur.com/Ay6hEZ4.jpeg"
        ],
        "text": [
            "Hallulla"
        ]
    },
    {
        "_id": "66e87dde067b01942ecb4a5e",
        "id": "c59b2bec-c4f5-4aa3-926d-3d17184d4655",
        "images": [
            "https://i.imgur.com/caOlzr1.png"
        ],
        "text": [
            "Hamaca",
            "hamaco",
            "hamacas",
            "hamaca",
            "hamacamos",
            "hamacáis",
            "hamacan",
            "hamacás",
            "hamacaba",
            "hamacabas",
            "hamacábamos",
            "hamacabais",
            "hamacaban",
            "hamaqué",
            "hamacaste",
            "hamacó",
            "hamacasteis",
            "hamacaron",
            "hamacaré",
            "hamacarás",
            "hamacará",
            "hamacaremos",
            "hamacaréis",
            "hamacarán",
            "hamacaría",
            "hamacarías",
            "hamacaríamos",
            "hamacaríais",
            "hamacarían",
            "hamacar",
            "hamacando",
            "hamacado",
            "hamacarse"
        ]
    },
    {
        "_id": "66e87ddf067b01942ecb4a5f",
        "id": "c03fd48a-a102-40e7-bcad-bfdb5e34c953",
        "images": [
            "https://i.imgur.com/6zCxx5a.png"
        ],
        "text": [
            "Hambre"
        ]
    },
    {
        "_id": "66e87de0067b01942ecb4a60",
        "id": "3495d496-9a28-4f15-a287-e2f1f9233673",
        "images": [
            "https://i.imgur.com/Cu9FzCd.png"
        ],
        "text": [
            "Hámster"
        ]
    },
    {
        "_id": "66e87de2067b01942ecb4a61",
        "id": "5608cd91-b10d-4da2-94c1-7b54bbb82df6",
        "images": [
            "https://i.imgur.com/FxqRdye.png"
        ],
        "text": [
            "Harina"
        ]
    },
    {
        "_id": "66e87de3067b01942ecb4a62",
        "id": "60538fd6-2bec-4893-bcd8-328959b5aade",
        "images": [
            "https://i.imgur.com/I6jbroc.png"
        ],
        "text": [
            "Hasta"
        ]
    },
    {
        "_id": "66e87de4067b01942ecb4a63",
        "id": "98421aea-7ad4-4f1a-a422-e668f0659279",
        "images": [
            "https://i.imgur.com/atZy45u.png",
            "https://i.imgur.com/v14pMGQ.jpeg"
        ],
        "text": [
            "Hebilla"
        ]
    },
    {
        "_id": "66e87de9067b01942ecb4a64",
        "id": "8aa07f2b-d992-44f0-b7eb-58b406684e2f",
        "images": [
            "https://i.imgur.com/Z6nxpCY.png",
            "https://i.imgur.com/f237YkQ.jpeg"
        ],
        "text": [
            "Hechizo",
            "hechizo",
            "hechizas",
            "hechiza",
            "hechizamos",
            "hechizáis",
            "hechizan",
            "hechizás",
            "hechizaba",
            "hechizabas",
            "hechizábamos",
            "hechizabais",
            "hechizaban",
            "hechicé",
            "hechizaste",
            "hechizó",
            "hechizasteis",
            "hechizaron",
            "hechizaré",
            "hechizarás",
            "hechizará",
            "hechizaremos",
            "hechizaréis",
            "hechizarán",
            "hechizaría",
            "hechizarías",
            "hechizaríamos",
            "hechizaríais",
            "hechizarían",
            "hechizar",
            "hechizando",
            "hechizado",
            "–",
            "Magia",
            "Brujería",
            "Encanto",
            "encanto",
            "encantas",
            "encanta",
            "encantamos",
            "encantáis",
            "encantan",
            "encantás",
            "encantaba",
            "encantabas",
            "encantábamos",
            "encantabais",
            "encantaban",
            "encanté",
            "encantaste",
            "encantó",
            "encantasteis",
            "encantaron",
            "encantaré",
            "encantarás",
            "encantará",
            "encantaremos",
            "encantaréis",
            "encantarán",
            "encantaría",
            "encantarías",
            "encantaríamos",
            "encantaríais",
            "encantarían",
            "encantar",
            "encantando",
            "encantado",
            "–"
        ]
    },
    {
        "_id": "66e87df3067b01942ecb4a65",
        "id": "e4bb6c08-3723-4015-9ce2-3ef6e5be626d",
        "images": [
            "https://i.imgur.com/0Co0elV.png",
            "https://i.imgur.com/2k2WCJF.jpeg"
        ],
        "text": [
            "Hediondo",
            "Hedionda",
            "Fétido",
            "Fétida",
            "Apestoso",
            "Apestosa",
            "Nauseabundo",
            "Nauseabunda"
        ]
    },
    {
        "_id": "66e87df4067b01942ecb4a66",
        "id": "fff35a76-c884-47e8-a59d-2f534331e245",
        "images": [
            "https://i.imgur.com/syuX5u2.png"
        ],
        "text": [
            "Helado",
            "hielo",
            "hielas",
            "hiela",
            "helamos",
            "heláis",
            "hielan",
            "helás",
            "helaba",
            "helabas",
            "helábamos",
            "helabais",
            "helaban",
            "helé",
            "helaste",
            "heló",
            "helasteis",
            "helaron",
            "helaré",
            "helarás",
            "helará",
            "helaremos",
            "helaréis",
            "helarán",
            "helaría",
            "helarías",
            "helaríamos",
            "helaríais",
            "helarían",
            "helar",
            "helando",
            "helado",
            "helarse"
        ]
    },
    {
        "_id": "66e87df6067b01942ecb4a67",
        "id": "288f6cd6-af7d-4f85-b95a-6b08d28fd94a",
        "images": [
            "https://i.imgur.com/aHHkWtP.png"
        ],
        "text": [
            "Hélice"
        ]
    },
    {
        "_id": "66e87df7067b01942ecb4a68",
        "id": "44dbdbe4-acf0-48fc-86e5-1aa53ad0cc33",
        "images": [
            "https://i.imgur.com/rlNhqiX.png"
        ],
        "text": [
            "Helicóptero"
        ]
    },
    {
        "_id": "66e87dfb067b01942ecb4a69",
        "id": "fb6550c5-b54e-4c52-9a5d-bf6eaabd6e0d",
        "images": [
            "https://i.imgur.com/h2cZ9Wh.png",
            "https://i.imgur.com/geFEZg4.jpeg"
        ],
        "text": [
            "Herencia",
            "Legado",
            "lego",
            "legas",
            "lega",
            "legamos",
            "legáis",
            "legan",
            "legás",
            "legaba",
            "legabas",
            "legábamos",
            "legabais",
            "legaban",
            "legué",
            "legaste",
            "legó",
            "legasteis",
            "legaron",
            "legaré",
            "legarás",
            "legará",
            "legaremos",
            "legaréis",
            "legarán",
            "legaría",
            "legarías",
            "legaríamos",
            "legaríais",
            "legarían",
            "legar",
            "legando",
            "legado",
            "–",
            "Sucesión"
        ]
    },
    {
        "_id": "66e87dfc067b01942ecb4a6a",
        "id": "6df03366-8fda-4270-b1af-798c9d488447",
        "images": [
            "https://i.imgur.com/74BrQaW.png"
        ],
        "text": [
            "Herida",
            "hiero",
            "hieres",
            "hiere",
            "herimos",
            "herís",
            "hieren",
            "hería",
            "herías",
            "heríamos",
            "heríais",
            "herían",
            "herí",
            "heriste",
            "hirió",
            "heristeis",
            "hirieron",
            "heriré",
            "herirás",
            "herirá",
            "heriremos",
            "heriréis",
            "herirán",
            "heriría",
            "herirías",
            "heriríamos",
            "heriríais",
            "herirían",
            "herir",
            "hiriendo",
            "herido",
            "herirse"
        ]
    },
    {
        "_id": "66e87e01067b01942ecb4a6b",
        "id": "98926171-b3d3-4797-9482-344888080e24",
        "images": [
            "https://i.imgur.com/iBREtg8.png",
            "https://i.imgur.com/h62cUXu.jpeg"
        ],
        "text": [
            "Hermanastro",
            "Hermanastra",
            "Medio Hermano",
            "Media Hermana"
        ]
    },
    {
        "_id": "66e87e03067b01942ecb4a6c",
        "id": "f7cf5671-a96d-4606-a72c-5a5c69acadcc",
        "images": [
            "https://i.imgur.com/dwLwmj0.png"
        ],
        "text": [
            "Hermano",
            "hermano",
            "hermanas",
            "hermana",
            "hermanamos",
            "hermanáis",
            "hermanan",
            "hermanás",
            "hermanaba",
            "hermanabas",
            "hermanábamos",
            "hermanabais",
            "hermanaban",
            "hermané",
            "hermanaste",
            "hermanó",
            "hermanasteis",
            "hermanaron",
            "hermanaré",
            "hermanarás",
            "hermanará",
            "hermanaremos",
            "hermanaréis",
            "hermanarán",
            "hermanaría",
            "hermanarías",
            "hermanaríamos",
            "hermanaríais",
            "hermanarían",
            "hermanar",
            "hermanando",
            "hermanado",
            "hermanarse",
            "Hermana",
            "hermano",
            "hermanas",
            "hermana",
            "hermanamos",
            "hermanáis",
            "hermanan",
            "hermanás",
            "hermanaba",
            "hermanabas",
            "hermanábamos",
            "hermanabais",
            "hermanaban",
            "hermané",
            "hermanaste",
            "hermanó",
            "hermanasteis",
            "hermanaron",
            "hermanaré",
            "hermanarás",
            "hermanará",
            "hermanaremos",
            "hermanaréis",
            "hermanarán",
            "hermanaría",
            "hermanarías",
            "hermanaríamos",
            "hermanaríais",
            "hermanarían",
            "hermanar",
            "hermanando",
            "hermanado",
            "hermanarse"
        ]
    },
    {
        "_id": "66e87e0c067b01942ecb4a6d",
        "id": "a533d952-a382-47f9-ab75-45edaa8c7de4",
        "images": [
            "https://i.imgur.com/K4lSOlU.png"
        ],
        "text": [
            "Hermoso",
            "Hermosa",
            "Bello",
            "Bella",
            "Lindo",
            "lindo",
            "lindas",
            "linda",
            "lindamos",
            "lindáis",
            "lindan",
            "lindás",
            "lindaba",
            "lindabas",
            "lindábamos",
            "lindabais",
            "lindaban",
            "lindé",
            "lindaste",
            "lindó",
            "lindasteis",
            "lindaron",
            "lindaré",
            "lindarás",
            "lindará",
            "lindaremos",
            "lindaréis",
            "lindarán",
            "lindaría",
            "lindarías",
            "lindaríamos",
            "lindaríais",
            "lindarían",
            "lindar",
            "lindando",
            "lindado",
            "–",
            "Linda",
            "lindo",
            "lindas",
            "linda",
            "lindamos",
            "lindáis",
            "lindan",
            "lindás",
            "lindaba",
            "lindabas",
            "lindábamos",
            "lindabais",
            "lindaban",
            "lindé",
            "lindaste",
            "lindó",
            "lindasteis",
            "lindaron",
            "lindaré",
            "lindarás",
            "lindará",
            "lindaremos",
            "lindaréis",
            "lindarán",
            "lindaría",
            "lindarías",
            "lindaríamos",
            "lindaríais",
            "lindarían",
            "lindar",
            "lindando",
            "lindado",
            "–",
            "Precioso",
            "Preciosa"
        ]
    },
    {
        "_id": "66e87e12067b01942ecb4a6e",
        "id": "d3db79d3-d9ac-4007-9777-375f37a1a266",
        "images": [
            "https://i.imgur.com/YDbSoFy.png"
        ],
        "text": [
            "Héroe",
            "Victorioso",
            "Victoriosa",
            "Triunfadora",
            "Triunfador"
        ]
    },
    {
        "_id": "66e87e14067b01942ecb4a6f",
        "id": "ca861e7b-01e9-45d8-852c-7ce1360d0302",
        "images": [
            "https://i.imgur.com/GxcSIbO.png"
        ],
        "text": [
            "Herradura"
        ]
    },
    {
        "_id": "66e87e16067b01942ecb4a70",
        "id": "39bcdf99-18b7-4735-ab9b-f4bc3fea036a",
        "images": [
            "https://i.imgur.com/oN0oTx4.png"
        ],
        "text": [
            "Hervidor",
            "Tetera Eléctrica"
        ]
    },
    {
        "_id": "66e87e18067b01942ecb4a71",
        "id": "7d37e369-0080-43bf-b622-83239fb0b4d3",
        "images": [
            "https://i.imgur.com/IrbW1cg.png"
        ],
        "text": [
            "Hervir",
            "hiervo",
            "hierves",
            "hierve",
            "hervimos",
            "hervís",
            "hierven",
            "hervía",
            "hervías",
            "hervíamos",
            "hervíais",
            "hervían",
            "herví",
            "herviste",
            "hirvió",
            "hervisteis",
            "hirvieron",
            "herviré",
            "hervirás",
            "hervirá",
            "herviremos",
            "herviréis",
            "hervirán",
            "herviría",
            "hervirías",
            "herviríamos",
            "herviríais",
            "hervirían",
            "hervir",
            "hirviendo",
            "hervido",
            "–"
        ]
    },
    {
        "_id": "66e87e19067b01942ecb4a72",
        "id": "b8cfedee-c75e-47dd-b25b-996fb63f26ad",
        "images": [
            "https://i.imgur.com/pW8WaxB.png"
        ],
        "text": [
            "Hielo",
            "hielo",
            "hielas",
            "hiela",
            "helamos",
            "heláis",
            "hielan",
            "helás",
            "helaba",
            "helabas",
            "helábamos",
            "helabais",
            "helaban",
            "helé",
            "helaste",
            "heló",
            "helasteis",
            "helaron",
            "helaré",
            "helarás",
            "helará",
            "helaremos",
            "helaréis",
            "helarán",
            "helaría",
            "helarías",
            "helaríamos",
            "helaríais",
            "helarían",
            "helar",
            "helando",
            "helado",
            "helarse"
        ]
    },
    {
        "_id": "66e87e1a067b01942ecb4a73",
        "id": "7a556177-0a1f-4e81-a365-57a55227fe70",
        "images": [
            "https://i.imgur.com/FnYYJ4h.png"
        ],
        "text": [
            "Hígado"
        ]
    },
    {
        "_id": "66e87e1b067b01942ecb4a74",
        "id": "4582df09-c571-4a64-99aa-3cab3a90047d",
        "images": [
            "https://i.imgur.com/mZ0lEDA.png"
        ],
        "text": [
            "Higo"
        ]
    },
    {
        "_id": "66e87e1e067b01942ecb4a75",
        "id": "9399c19d-2a3e-4675-9aaf-0c85e3de9c70",
        "images": [
            "https://i.imgur.com/MiqAlh8.png"
        ],
        "text": [
            "Hijo",
            "Hija"
        ]
    },
    {
        "_id": "66e87e20067b01942ecb4a76",
        "id": "95de5d42-c0a9-436a-a7a5-a64b3b4f2f7c",
        "images": [
            "https://i.imgur.com/yCd0Mzy.png",
            "https://i.imgur.com/5Axhaxg.jpeg"
        ],
        "text": [
            "Hijastro",
            "Hijastra"
        ]
    },
    {
        "_id": "66e87e22067b01942ecb4a77",
        "id": "2e53f103-8da3-41d3-8cb0-665ff61ffd21",
        "images": [
            "https://i.imgur.com/h9c1X8b.png"
        ],
        "text": [
            "Hilo",
            "hilo",
            "hilas",
            "hila",
            "hilamos",
            "hiláis",
            "hilan",
            "hilás",
            "hilaba",
            "hilabas",
            "hilábamos",
            "hilabais",
            "hilaban",
            "hilé",
            "hilaste",
            "hiló",
            "hilasteis",
            "hilaron",
            "hilaré",
            "hilarás",
            "hilará",
            "hilaremos",
            "hilaréis",
            "hilarán",
            "hilaría",
            "hilarías",
            "hilaríamos",
            "hilaríais",
            "hilarían",
            "hilar",
            "hilando",
            "hilado",
            "–"
        ]
    },
    {
        "_id": "66e87e23067b01942ecb4a78",
        "id": "fdb65ef0-8916-48d5-8289-0f5f494aa1dd",
        "images": [
            "https://i.imgur.com/8v5VZAN.png"
        ],
        "text": [
            "Himno"
        ]
    },
    {
        "_id": "66e87e24067b01942ecb4a79",
        "id": "c5c81831-7aa2-41c8-8fb5-607f67a3a1e2",
        "images": [
            "https://i.imgur.com/XJroqGj.png"
        ],
        "text": [
            "Hincarse",
            "me hinco",
            "te hincas",
            "se hinca",
            "nos hincamos",
            "os hincáis",
            "se hincan",
            "te hincás",
            "me hincaba",
            "te hincabas",
            "se hincaba",
            "nos hincábamos",
            "os hincabais",
            "se hincaban",
            "me hinqué",
            "te hincaste",
            "se hincó",
            "os hincasteis",
            "se hincaron",
            "me hincaré",
            "te hincarás",
            "se hincará",
            "nos hincaremos",
            "os hincaréis",
            "se hincarán",
            "me hincaría",
            "te hincarías",
            "se hincaría",
            "nos hincaríamos",
            "os hincaríais",
            "se hincarían",
            "hincarse",
            "hincando",
            "hincándose",
            "hincado",
            "hincar"
        ]
    },
    {
        "_id": "66e87e26067b01942ecb4a7a",
        "id": "0ecbd337-e4ef-4032-8d8e-bc218c330b5e",
        "images": [
            "https://i.imgur.com/X6a7zD4.png"
        ],
        "text": [
            "Hincha",
            "hincho",
            "hinchas",
            "hincha",
            "hinchamos",
            "hincháis",
            "hinchan",
            "hinchás",
            "hinchaba",
            "hinchabas",
            "hinchábamos",
            "hinchabais",
            "hinchaban",
            "hinché",
            "hinchaste",
            "hinchó",
            "hinchasteis",
            "hincharon",
            "hincharé",
            "hincharás",
            "hinchará",
            "hincharemos",
            "hincharéis",
            "hincharán",
            "hincharía",
            "hincharías",
            "hincharíamos",
            "hincharíais",
            "hincharían",
            "hinchar",
            "hinchando",
            "hinchado",
            "hincharse"
        ]
    },
    {
        "_id": "66e87e28067b01942ecb4a7b",
        "id": "aa82a019-8c76-46d7-a903-ed1dd8b31c41",
        "images": [
            "https://i.imgur.com/dS94Dga.png"
        ],
        "text": [
            "Hinchado",
            "hincho",
            "hinchas",
            "hincha",
            "hinchamos",
            "hincháis",
            "hinchan",
            "hinchás",
            "hinchaba",
            "hinchabas",
            "hinchábamos",
            "hinchabais",
            "hinchaban",
            "hinché",
            "hinchaste",
            "hinchó",
            "hinchasteis",
            "hincharon",
            "hincharé",
            "hincharás",
            "hinchará",
            "hincharemos",
            "hincharéis",
            "hincharán",
            "hincharía",
            "hincharías",
            "hincharíamos",
            "hincharíais",
            "hincharían",
            "hinchar",
            "hinchando",
            "hinchado",
            "hincharse",
            "Hinchada",
            "hincho",
            "hinchas",
            "hincha",
            "hinchamos",
            "hincháis",
            "hinchan",
            "hinchás",
            "hinchaba",
            "hinchabas",
            "hinchábamos",
            "hinchabais",
            "hinchaban",
            "hinché",
            "hinchaste",
            "hinchó",
            "hinchasteis",
            "hincharon",
            "hincharé",
            "hincharás",
            "hinchará",
            "hincharemos",
            "hincharéis",
            "hincharán",
            "hincharía",
            "hincharías",
            "hincharíamos",
            "hincharíais",
            "hincharían",
            "hinchar",
            "hinchando",
            "hinchado",
            "hincharse"
        ]
    },
    {
        "_id": "66e87e29067b01942ecb4a7c",
        "id": "70bef492-e1f8-4206-bbe7-d474f2fa949a",
        "images": [
            "https://i.imgur.com/uIP2zzQ.png"
        ],
        "text": [
            "Hipnotizar",
            "hipnotizo",
            "hipnotizas",
            "hipnotiza",
            "hipnotizamos",
            "hipnotizáis",
            "hipnotizan",
            "hipnotizás",
            "hipnotizaba",
            "hipnotizabas",
            "hipnotizábamos",
            "hipnotizabais",
            "hipnotizaban",
            "hipnoticé",
            "hipnotizaste",
            "hipnotizó",
            "hipnotizasteis",
            "hipnotizaron",
            "hipnotizaré",
            "hipnotizarás",
            "hipnotizará",
            "hipnotizaremos",
            "hipnotizaréis",
            "hipnotizarán",
            "hipnotizaría",
            "hipnotizarías",
            "hipnotizaríamos",
            "hipnotizaríais",
            "hipnotizarían",
            "hipnotizar",
            "hipnotizando",
            "hipnotizado",
            "–"
        ]
    },
    {
        "_id": "66e87e2b067b01942ecb4a7d",
        "id": "6447bab1-3a24-4a75-8547-cf9994d6f9df",
        "images": [
            "https://i.imgur.com/RGXtA2H.png"
        ],
        "text": [
            "Hipo",
            "hipo",
            "hipas",
            "hipa",
            "hipamos",
            "hipáis",
            "hipan",
            "hipás",
            "hipaba",
            "hipabas",
            "hipábamos",
            "hipabais",
            "hipaban",
            "hipé",
            "hipaste",
            "hipó",
            "hipasteis",
            "hiparon",
            "hiparé",
            "hiparás",
            "hipará",
            "hiparemos",
            "hiparéis",
            "hiparán",
            "hiparía",
            "hiparías",
            "hiparíamos",
            "hiparíais",
            "hiparían",
            "hipar",
            "hipando",
            "hipado",
            "–"
        ]
    },
    {
        "_id": "66e87e2e067b01942ecb4a7e",
        "id": "5d1f2213-4c93-4a90-8dc4-2de5731a6cc9",
        "images": [
            "https://i.imgur.com/f6Q5oBF.png"
        ],
        "text": [
            "Hipoacúsico",
            "Hipoacúsica"
        ]
    },
    {
        "_id": "66e87e2f067b01942ecb4a7f",
        "id": "7a4537cc-bbff-485f-ad1a-5b92d0ad5aa6",
        "images": [
            "https://i.imgur.com/ntL8Lpi.png"
        ],
        "text": [
            "Hipócrita"
        ]
    },
    {
        "_id": "66e87e30067b01942ecb4a80",
        "id": "aced7c1a-eec8-4521-ad29-da43e75dc8d8",
        "images": [
            "https://i.imgur.com/tUBxIBP.png"
        ],
        "text": [
            "Hipopótamo"
        ]
    },
    {
        "_id": "66e87e32067b01942ecb4a81",
        "id": "9c2b9825-2016-44fc-903b-17e913172191",
        "images": [
            "https://i.imgur.com/niFOLGo.png",
            "https://i.imgur.com/6rq8NYp.jpeg"
        ],
        "text": [
            "Historia",
            "historio",
            "historias",
            "historia",
            "historiamos",
            "historiáis",
            "historian",
            "historiás",
            "historiaba",
            "historiabas",
            "historiábamos",
            "historiabais",
            "historiaban",
            "historié",
            "historiaste",
            "historió",
            "historiasteis",
            "historiaron",
            "historiaré",
            "historiarás",
            "historiará",
            "historiaremos",
            "historiaréis",
            "historiarán",
            "historiaría",
            "historiarías",
            "historiaríamos",
            "historiaríais",
            "historiarían",
            "historiar",
            "historiando",
            "historiado",
            "–"
        ]
    },
    {
        "_id": "66e87e36067b01942ecb4a82",
        "id": "7be70993-ab18-490b-b18a-896d17e7fc60",
        "images": [
            "https://i.imgur.com/LdXzY1l.png",
            "https://i.imgur.com/ZkpK5iL.jpeg"
        ],
        "text": [
            "Hogar",
            "Casa",
            "caso",
            "casas",
            "casa",
            "casamos",
            "casáis",
            "casan",
            "casás",
            "casaba",
            "casabas",
            "casábamos",
            "casabais",
            "casaban",
            "casé",
            "casaste",
            "casó",
            "casasteis",
            "casaron",
            "casaré",
            "casarás",
            "casará",
            "casaremos",
            "casaréis",
            "casarán",
            "casaría",
            "casarías",
            "casaríamos",
            "casaríais",
            "casarían",
            "casar",
            "casando",
            "casado",
            "casarse",
            "Domicilio",
            "domicilio",
            "domicilias",
            "domicilia",
            "domiciliamos",
            "domiciliáis",
            "domicilian",
            "domiciliás",
            "domiciliaba",
            "domiciliabas",
            "domiciliábamos",
            "domiciliabais",
            "domiciliaban",
            "domicilié",
            "domiciliaste",
            "domicilió",
            "domiciliasteis",
            "domiciliaron",
            "domiciliaré",
            "domiciliarás",
            "domiciliará",
            "domiciliaremos",
            "domiciliaréis",
            "domiciliarán",
            "domiciliaría",
            "domiciliarías",
            "domiciliaríamos",
            "domiciliaríais",
            "domiciliarían",
            "domiciliar",
            "domiciliando",
            "domiciliado",
            "domiciliarse",
            "Morada",
            "moro",
            "moras",
            "mora",
            "moramos",
            "moráis",
            "moran",
            "morás",
            "moraba",
            "morabas",
            "morábamos",
            "morabais",
            "moraban",
            "moré",
            "moraste",
            "moró",
            "morasteis",
            "moraron",
            "moraré",
            "morarás",
            "morará",
            "moraremos",
            "moraréis",
            "morarán",
            "moraría",
            "morarías",
            "moraríamos",
            "moraríais",
            "morarían",
            "morar",
            "morando",
            "morado",
            "–"
        ]
    },
    {
        "_id": "66e87e38067b01942ecb4a83",
        "id": "d61c70a4-ac57-47e6-acae-d6702a498ed4",
        "images": [
            "https://i.imgur.com/1UpMvdT.png"
        ],
        "text": [
            "Hoja De Árbol"
        ]
    },
    {
        "_id": "66e87e39067b01942ecb4a84",
        "id": "c701b31b-4642-45d2-85e8-709e90595dac",
        "images": [
            "https://i.imgur.com/pU1raF5.png"
        ],
        "text": [
            "Hoja De Papel"
        ]
    },
    {
        "_id": "66e87e3a067b01942ecb4a85",
        "id": "2d4dc733-ec0b-4259-89df-2ef77cd91403",
        "images": [
            "https://i.imgur.com/t4NFmAR.png"
        ],
        "text": [
            "Hola"
        ]
    },
    {
        "_id": "66e87e3c067b01942ecb4a86",
        "id": "9b1d68b1-6d44-4127-8a82-09dce8eb6b41",
        "images": [
            "https://i.imgur.com/V4IvYZT.png",
            "https://i.imgur.com/cAD5bOl.jpeg"
        ],
        "text": [
            "Holanda"
        ]
    },
    {
        "_id": "66e87e3d067b01942ecb4a87",
        "id": "41a7393e-0b7b-48c1-8217-307d04fa2801",
        "images": [
            "https://i.imgur.com/Sw7Qf3h.png"
        ],
        "text": [
            "Hombre"
        ]
    },
    {
        "_id": "66e87e3e067b01942ecb4a88",
        "id": "abbae7db-75cd-4a08-9513-d940fe18c8e5",
        "images": [
            "https://i.imgur.com/xHCn9iU.png"
        ],
        "text": [
            "Homenaje"
        ]
    },
    {
        "_id": "66e87e40067b01942ecb4a89",
        "id": "feaf480c-14c1-4a89-844e-2c87e27b1690",
        "images": [
            "https://i.imgur.com/Vpj4VNc.png"
        ],
        "text": [
            "Hongo"
        ]
    },
    {
        "_id": "66e87e41067b01942ecb4a8a",
        "id": "0fb957a8-531b-4847-88ea-0de291aa1a5f",
        "images": [
            "https://i.imgur.com/l48Kz0J.png"
        ],
        "text": [
            "Honor"
        ]
    },
    {
        "_id": "66e87e42067b01942ecb4a8b",
        "id": "2c125aec-fa5f-42da-b31c-9541d3656e7c",
        "images": [
            "https://i.imgur.com/F6WYbDW.png"
        ],
        "text": [
            "Hora"
        ]
    },
    {
        "_id": "66e87e45067b01942ecb4a8c",
        "id": "dec68197-8e33-4467-8039-5d5dc0902196",
        "images": [
            "https://i.imgur.com/QYVcplS.png",
            "https://i.imgur.com/RFNXItP.jpeg"
        ],
        "text": [
            "Horario",
            "Cronograma"
        ]
    },
    {
        "_id": "66e87e46067b01942ecb4a8d",
        "id": "6423209f-17c0-435b-bad9-5810d1b9458e",
        "images": [
            "https://i.imgur.com/JmlhebA.png"
        ],
        "text": [
            "Hormiga"
        ]
    },
    {
        "_id": "66e87e47067b01942ecb4a8e",
        "id": "c08aaa98-6e51-4450-af88-9862c958f6bf",
        "images": [
            "https://i.imgur.com/OiNHyhq.png"
        ],
        "text": [
            "Horno"
        ]
    },
    {
        "_id": "66e87e49067b01942ecb4a8f",
        "id": "9ae9f1cc-f1db-4a36-b3b2-8efae27800fa",
        "images": [
            "https://i.imgur.com/wb2HrBN.png"
        ],
        "text": [
            "Horóscopo"
        ]
    },
    {
        "_id": "66e87e4d067b01942ecb4a90",
        "id": "f67ffa05-c0ec-40e2-8c83-bc9b075e0d55",
        "images": [
            "https://i.imgur.com/EnnUH3F.png",
            "https://i.imgur.com/QlttzVH.jpeg"
        ],
        "text": [
            "Hospital",
            "Clínica",
            "Sanatorio"
        ]
    },
    {
        "_id": "66e87e4e067b01942ecb4a91",
        "id": "104feb9f-4d80-48ed-88e7-9c1a207abbde",
        "images": [
            "https://i.imgur.com/E4o4Srx.png"
        ],
        "text": [
            "Hotel"
        ]
    },
    {
        "_id": "66e87e4f067b01942ecb4a92",
        "id": "0b36ec6b-a37b-4d35-b8d2-268711b5b5ce",
        "images": [
            "https://i.imgur.com/dHGgplc.png"
        ],
        "text": [
            "Hoy"
        ]
    },
    {
        "_id": "66e87e52067b01942ecb4a93",
        "id": "0dd90100-61a9-48f4-9088-439d73937eea",
        "images": [
            "https://i.imgur.com/Bf1PjSv.png"
        ],
        "text": [
            "Huaso",
            "Huasa"
        ]
    },
    {
        "_id": "66e87e53067b01942ecb4a94",
        "id": "1164e05a-8885-4122-96a4-75277fb9586d",
        "images": [
            "https://i.imgur.com/LfL0muM.png"
        ],
        "text": [
            "Huelga",
            "huelgo",
            "huelgas",
            "huelga",
            "holgamos",
            "holgáis",
            "huelgan",
            "holgás",
            "holgaba",
            "holgabas",
            "holgábamos",
            "holgabais",
            "holgaban",
            "holgué",
            "holgaste",
            "holgó",
            "holgasteis",
            "holgaron",
            "holgaré",
            "holgarás",
            "holgará",
            "holgaremos",
            "holgaréis",
            "holgarán",
            "holgaría",
            "holgarías",
            "holgaríamos",
            "holgaríais",
            "holgarían",
            "holgar",
            "holgando",
            "holgado",
            "holgarse"
        ]
    },
    {
        "_id": "66e87e54067b01942ecb4a95",
        "id": "25e7d0e4-842b-42ce-ace1-3970968a8a7b",
        "images": [
            "https://i.imgur.com/MZft5b9.png"
        ],
        "text": [
            "Huemul"
        ]
    },
    {
        "_id": "66e87e57067b01942ecb4a96",
        "id": "19c86eb2-51eb-4597-b356-20787e8143b8",
        "images": [
            "https://i.imgur.com/AQ7YqMP.png"
        ],
        "text": [
            "Huérfano",
            "Huérfana"
        ]
    },
    {
        "_id": "66e87e58067b01942ecb4a97",
        "id": "ef95ddd2-1e93-4c96-90a0-2705549c652e",
        "images": [
            "https://i.imgur.com/xCWcgUC.png"
        ],
        "text": [
            "Huesillo"
        ]
    },
    {
        "_id": "66e87e59067b01942ecb4a98",
        "id": "75159118-5496-4dc9-89a3-82f141a99f95",
        "images": [
            "https://i.imgur.com/IGJc57y.png"
        ],
        "text": [
            "Hueso"
        ]
    },
    {
        "_id": "66e87e5b067b01942ecb4a99",
        "id": "6cf69fbe-850b-45a0-ae20-6e601cc22654",
        "images": [
            "https://i.imgur.com/yHIK2Sx.png",
            "https://i.imgur.com/TN47LQa.jpeg"
        ],
        "text": [
            "Huevo"
        ]
    },
    {
        "_id": "66e87e5c067b01942ecb4a9a",
        "id": "024ad115-6203-4c91-95fd-ec9f65078de5",
        "images": [
            "https://i.imgur.com/6QwLyRI.png"
        ],
        "text": [
            "Huincha"
        ]
    },
    {
        "_id": "66e87e5d067b01942ecb4a9b",
        "id": "afede289-2fae-4e9f-ad63-0a1d356c9530",
        "images": [
            "https://i.imgur.com/OoToFgi.png"
        ],
        "text": [
            "Huir",
            "huyo",
            "huyes",
            "huye",
            "huimos",
            "huis",
            "huyen",
            "huía",
            "huías",
            "huíamos",
            "huíais",
            "huían",
            "hui",
            "huiste",
            "huyó",
            "huisteis",
            "huyeron",
            "huiré",
            "huirás",
            "huirá",
            "huiremos",
            "huiréis",
            "huirán",
            "huiría",
            "huirías",
            "huiríamos",
            "huiríais",
            "huirían",
            "huir",
            "huyendo",
            "huido",
            "–"
        ]
    },
    {
        "_id": "66e87e60067b01942ecb4a9c",
        "id": "bb456e9c-22a1-4dc6-bf54-6edacb54c39e",
        "images": [
            "https://i.imgur.com/wXT14zX.png"
        ],
        "text": [
            "Humano",
            "Humana"
        ]
    },
    {
        "_id": "66e87e61067b01942ecb4a9d",
        "id": "e82e1d66-b072-482a-9be3-971074ba9612",
        "images": [
            "https://i.imgur.com/AuBxlE8.png"
        ],
        "text": [
            "Húmedo"
        ]
    },
    {
        "_id": "66e87e63067b01942ecb4a9e",
        "id": "84e99934-5601-4ac8-8621-991abf7ed16a",
        "images": [
            "https://i.imgur.com/dti7l2i.png"
        ],
        "text": [
            "Humilde"
        ]
    },
    {
        "_id": "66e87e64067b01942ecb4a9f",
        "id": "0d3763c9-6ee1-4e61-a7fc-862cb430b29b",
        "images": [
            "https://i.imgur.com/YyADtnb.png"
        ],
        "text": [
            "Humillar",
            "humillo",
            "humillas",
            "humilla",
            "humillamos",
            "humilláis",
            "humillan",
            "humillás",
            "humillaba",
            "humillabas",
            "humillábamos",
            "humillabais",
            "humillaban",
            "humillé",
            "humillaste",
            "humilló",
            "humillasteis",
            "humillaron",
            "humillaré",
            "humillarás",
            "humillará",
            "humillaremos",
            "humillaréis",
            "humillarán",
            "humillaría",
            "humillarías",
            "humillaríamos",
            "humillaríais",
            "humillarían",
            "humillar",
            "humillando",
            "humillado",
            "humillarse"
        ]
    },
    {
        "_id": "66e87e65067b01942ecb4aa0",
        "id": "6c0dac2f-51b5-45e5-93f4-7a9f70d0eefc",
        "images": [
            "https://i.imgur.com/GMyq333.png"
        ],
        "text": [
            "Humo"
        ]
    },
    {
        "_id": "66e87e67067b01942ecb4aa1",
        "id": "b5abd55f-44e7-4151-8051-e411fd68ee75",
        "images": [
            "https://i.imgur.com/ye3FS4U.png"
        ],
        "text": [
            "Hungría"
        ]
    },
    {
        "_id": "66e87e68067b01942ecb4aa2",
        "id": "bea3003b-0f83-4bcb-b856-c754d29ed3c9",
        "images": [
            "https://i.imgur.com/UyqAEX7.png"
        ],
        "text": [
            "Huracán"
        ]
    },
    {
        "_id": "66e87e69067b01942ecb4aa3",
        "id": "6f064499-1338-4b8f-a530-1f9268e62056",
        "images": [
            "https://i.imgur.com/lJ71ELR.png"
        ],
        "text": [
            "Houshou Marine"
        ]
    },
    {
        "_id": "66e87e6c067b01942ecb4aa4",
        "id": "531c339e-a639-4e40-99f0-ce895bf97aeb",
        "images": [
            "https://i.imgur.com/w2rspYY.png",
            "https://i.imgur.com/HUxiwTg.jpeg"
        ],
        "text": [
            "Horno De Microondas",
            "Microondas"
        ]
    }
]